ucuu/__init__.py
ucuu/decorator.py
ucuu/log.py
ucuu-0.1.1.dist-info/LICENSE
ucuu-0.1.1.dist-info/METADATA
ucuu-0.1.1.dist-info/WHEEL
ucuu-0.1.1.dist-info/top_level.txt
ucuu-0.1.1.dist-info/RECORD
