Metadata-Version: 2.1
Name: ucuu
Version: 0.1.1
Summary: A lightweight and extensible Python utility toolkit for productivity and automation.
Author-email: wZuck <wzuck.wang@gmail.com>
License: This is free and unencumbered software released into the public domain.
Project-URL: homepage, https://wzuck.github.io/ucuu/
Project-URL: repository, https://github.com/wZuck/ucuu
Project-URL: documentation, https://github.com/wZuck/ucuu
Project-URL: pypi, https://pypi.org/project/ucuu/
Classifier: Programming Language :: Python :: 3
Classifier: Programming Language :: Python :: 3.8
Classifier: License :: OSI Approved :: MIT License
Classifier: Operating System :: OS Independent
Classifier: Intended Audience :: Developers
Classifier: Topic :: Software Development :: Libraries :: Python Modules
Requires-Python: >=3.8
License-File: LICENSE
Requires-Dist: rich >=14.0.0
Requires-Dist: black >=24.0.0
Provides-Extra: docs
Requires-Dist: ghp-import >=2.1.0 ; extra == 'docs'
Provides-Extra: publish
Requires-Dist: build >=1.0.0 ; extra == 'publish'
Requires-Dist: twine >=4.0.0 ; extra == 'publish'
